{
  "train_losses": [
    {
      "epoch": 1,
      "loss": 1.4736672101373023
    },
    {
      "epoch": 2,
      "loss": 1.0524158254265785
    },
    {
      "epoch": 3,
      "loss": 0.8987507466226816
    },
    {
      "epoch": 4,
      "loss": 0.7907209826464002
    },
    {
      "epoch": 5,
      "loss": 0.7112064644355666
    },
    {
      "epoch": 6,
      "loss": 0.6541563589125872
    },
    {
      "epoch": 7,
      "loss": 0.6148230074481531
    },
    {
      "epoch": 8,
      "loss": 0.5760435309599746
    },
    {
      "epoch": 9,
      "loss": 0.5468443065712397
    },
    {
      "epoch": 10,
      "loss": 0.5175868006084453
    },
    {
      "epoch": 11,
      "loss": 0.4951708235523917
    },
    {
      "epoch": 12,
      "loss": 0.47507600994272664
    },
    {
      "epoch": 13,
      "loss": 0.45827104058116674
    },
    {
      "epoch": 14,
      "loss": 0.43769500040533865
    },
    {
      "epoch": 15,
      "loss": 0.4243342079306868
    },
    {
      "epoch": 16,
      "loss": 0.4103444117460061
    },
    {
      "epoch": 17,
      "loss": 0.3976525199938227
    },
    {
      "epoch": 18,
      "loss": 0.3884973710148849
    },
    {
      "epoch": 19,
      "loss": 0.37309833806516096
    },
    {
      "epoch": 20,
      "loss": 0.3610939104956659
    },
    {
      "epoch": 21,
      "loss": 0.35284127070653165
    },
    {
      "epoch": 22,
      "loss": 0.342626923610541
    },
    {
      "epoch": 23,
      "loss": 0.335168979215351
    },
    {
      "epoch": 24,
      "loss": 0.3221757575361566
    },
    {
      "epoch": 25,
      "loss": 0.31648700404912233
    },
    {
      "epoch": 26,
      "loss": 0.3060012187131427
    },
    {
      "epoch": 27,
      "loss": 0.30246052014726127
    },
    {
      "epoch": 28,
      "loss": 0.2923217292621054
    },
    {
      "epoch": 29,
      "loss": 0.28978914699771186
    },
    {
      "epoch": 30,
      "loss": 0.28168156823482027
    },
    {
      "epoch": 31,
      "loss": 0.27886458401652897
    },
    {
      "epoch": 32,
      "loss": 0.27312331363050774
    },
    {
      "epoch": 33,
      "loss": 0.26264088935303415
    },
    {
      "epoch": 34,
      "loss": 0.25412536501376465
    },
    {
      "epoch": 35,
      "loss": 0.25365815963596106
    },
    {
      "epoch": 36,
      "loss": 0.2474985001185401
    },
    {
      "epoch": 37,
      "loss": 0.24621560394933278
    },
    {
      "epoch": 38,
      "loss": 0.2422158173708753
    },
    {
      "epoch": 39,
      "loss": 0.23472245054488833
    },
    {
      "epoch": 40,
      "loss": 0.22314360094341365
    },
    {
      "epoch": 41,
      "loss": 0.22621504780413074
    },
    {
      "epoch": 42,
      "loss": 0.22122205997055228
    },
    {
      "epoch": 43,
      "loss": 0.2156181693161753
    },
    {
      "epoch": 44,
      "loss": 0.21500752942467277
    },
    {
      "epoch": 45,
      "loss": 0.2070150692650879
    },
    {
      "epoch": 46,
      "loss": 0.2056706724900075
    },
    {
      "epoch": 47,
      "loss": 0.2041795910124413
    },
    {
      "epoch": 48,
      "loss": 0.19192218932915817
    },
    {
      "epoch": 49,
      "loss": 0.1939921399620785
    },
    {
      "epoch": 50,
      "loss": 0.19094599354800515
    }
  ],
  "val_accuracies": [
    {
      "epoch": 1,
      "accuracy": 49.36
    },
    {
      "epoch": 2,
      "accuracy": 65.9
    },
    {
      "epoch": 3,
      "accuracy": 68.44
    },
    {
      "epoch": 4,
      "accuracy": 69.36
    },
    {
      "epoch": 5,
      "accuracy": 71.64
    },
    {
      "epoch": 6,
      "accuracy": 74.48
    },
    {
      "epoch": 7,
      "accuracy": 74.42
    },
    {
      "epoch": 8,
      "accuracy": 76.72
    },
    {
      "epoch": 9,
      "accuracy": 74.22
    },
    {
      "epoch": 10,
      "accuracy": 79.28
    },
    {
      "epoch": 11,
      "accuracy": 79.66
    },
    {
      "epoch": 12,
      "accuracy": 80.8
    },
    {
      "epoch": 13,
      "accuracy": 81.92
    },
    {
      "epoch": 14,
      "accuracy": 82.4
    },
    {
      "epoch": 15,
      "accuracy": 81.3
    },
    {
      "epoch": 16,
      "accuracy": 82.66
    },
    {
      "epoch": 17,
      "accuracy": 83.44
    },
    {
      "epoch": 18,
      "accuracy": 82.14
    },
    {
      "epoch": 19,
      "accuracy": 84.86
    },
    {
      "epoch": 20,
      "accuracy": 82.28
    },
    {
      "epoch": 21,
      "accuracy": 84.1
    },
    {
      "epoch": 22,
      "accuracy": 83.58
    },
    {
      "epoch": 23,
      "accuracy": 83.18
    },
    {
      "epoch": 24,
      "accuracy": 83.28
    },
    {
      "epoch": 25,
      "accuracy": 83.98
    },
    {
      "epoch": 26,
      "accuracy": 86.04
    },
    {
      "epoch": 27,
      "accuracy": 84.98
    },
    {
      "epoch": 28,
      "accuracy": 85.28
    },
    {
      "epoch": 29,
      "accuracy": 85.7
    },
    {
      "epoch": 30,
      "accuracy": 86.08
    },
    {
      "epoch": 31,
      "accuracy": 84.88
    },
    {
      "epoch": 32,
      "accuracy": 85.76
    },
    {
      "epoch": 33,
      "accuracy": 84.68
    },
    {
      "epoch": 34,
      "accuracy": 86.02
    },
    {
      "epoch": 35,
      "accuracy": 86.32
    },
    {
      "epoch": 36,
      "accuracy": 85.9
    },
    {
      "epoch": 37,
      "accuracy": 85.74
    },
    {
      "epoch": 38,
      "accuracy": 87.28
    },
    {
      "epoch": 39,
      "accuracy": 86.6
    },
    {
      "epoch": 40,
      "accuracy": 86.56
    },
    {
      "epoch": 41,
      "accuracy": 87.74
    },
    {
      "epoch": 42,
      "accuracy": 87.24
    },
    {
      "epoch": 43,
      "accuracy": 87.62
    },
    {
      "epoch": 44,
      "accuracy": 86.12
    },
    {
      "epoch": 45,
      "accuracy": 86.96
    },
    {
      "epoch": 46,
      "accuracy": 85.94
    },
    {
      "epoch": 47,
      "accuracy": 87.26
    },
    {
      "epoch": 48,
      "accuracy": 87.94
    },
    {
      "epoch": 49,
      "accuracy": 86.96
    },
    {
      "epoch": 50,
      "accuracy": 87.6
    }
  ],
  "test_accuracy": 87.27,
  "training_time": 238.9520823955536
}